clisnips/__init__.py
clisnips/__main__.py
clisnips/cli/__init__.py
clisnips/cli/app.py
clisnips/cli/command.py
clisnips/cli/commands/_import.py
clisnips/cli/commands/config.py
clisnips/cli/commands/dump.py
clisnips/cli/commands/export.py
clisnips/cli/commands/install_key_bindings.py
clisnips/cli/commands/logs.py
clisnips/cli/commands/optimize.py
clisnips/cli/commands/version.py
clisnips/cli/parser.py
clisnips/cli/utils.py
clisnips/config/__init__.py
clisnips/config/envs.py
clisnips/config/palette.py
clisnips/config/paths.py
clisnips/config/settings.py
clisnips/config/state.py
clisnips/database/__init__.py
clisnips/database/offset_pager.py
clisnips/database/pager.py
clisnips/database/scrolling_pager.py
clisnips/database/search_pager.py
clisnips/database/snippets_db.py
clisnips/dic.py
clisnips/exceptions.py
clisnips/exporters/__init__.py
clisnips/exporters/_json.py
clisnips/exporters/base.py
clisnips/exporters/toml.py
clisnips/exporters/xml.py
clisnips/importers/__init__.py
clisnips/importers/_json.py
clisnips/importers/base.py
clisnips/importers/clicompanion.py
clisnips/importers/toml.py
clisnips/importers/xml.py
clisnips/log/cli.py
clisnips/log/tui.py
clisnips/resources/key-bindings.bash
clisnips/resources/key-bindings.zsh
clisnips/resources/schema.sql
clisnips/stores/__init__.py
clisnips/stores/snippets.py
clisnips/syntax/__init__.py
clisnips/syntax/command/__init__.py
clisnips/syntax/command/err.py
clisnips/syntax/command/nodes.py
clisnips/syntax/command/parser.py
clisnips/syntax/command/renderer.py
clisnips/syntax/documentation/__init__.py
clisnips/syntax/documentation/executor.py
clisnips/syntax/documentation/lexer.py
clisnips/syntax/documentation/nodes.py
clisnips/syntax/documentation/parser.py
clisnips/syntax/llk_parser.py
clisnips/syntax/string_lexer.py
clisnips/syntax/token.py
clisnips/tui/__init__.py
clisnips/tui/animation.py
clisnips/tui/app.py
clisnips/tui/components/__init__.py
clisnips/tui/components/app_bar.py
clisnips-0.6.0.dist-info/LICENSE
clisnips-0.6.0.dist-info/METADATA
clisnips-0.6.0.dist-info/WHEEL
clisnips-0.6.0.dist-info/entry_points.txt
clisnips-0.6.0.dist-info/RECORD
