Metadata-Version: 2.1
Name: clisnips
Version: 0.6.0
Summary: A command-line snippets manager.
Home-page: https://github.com/ju1ius/clisnips
License: GPL-3.0+
Keywords: snippet,snippets,cli,tui
Author: ju1ius
Author-email: jules.bernable@gmail.com
Requires-Python: >=3.11,<4.0
Classifier: Development Status :: 3 - Alpha
Classifier: Environment :: Console
Classifier: Environment :: Console :: Curses
Classifier: License :: OSI Approved :: GNU General Public License v3 or later (GPLv3+)
Classifier: Operating System :: Microsoft :: Windows
Classifier: Operating System :: POSIX
Classifier: Operating System :: Unix
Classifier: Programming Language :: Python
Classifier: Programming Language :: Python :: 3
Classifier: Programming Language :: Python :: 3.11
Classifier: Programming Language :: Python :: 3.12
Classifier: Programming Language :: Python :: Implementation :: CPython
Classifier: Topic :: System :: System Shells
Classifier: Topic :: Terminals
Classifier: Topic :: Terminals :: Terminal Emulators/X Terminals
Classifier: Topic :: Utilities
Requires-Dist: observ (>=0.14,<0.15)
Requires-Dist: pydantic (>=2.4.2,<3.0.0)
Requires-Dist: pygments (>=2.16.1,<3.0.0)
Requires-Dist: tomlkit (>=0.12.3,<0.13.0)
Requires-Dist: typing-extensions (>=4.8.0,<5.0.0)
Requires-Dist: urwid (>=2.2.3,<3.0.0)
Project-URL: Repository, https://github.com/ju1ius/clisnips
